{
  "name": "toggle-group-demo",
  "type": "registry:example",
  "files": [
    {
      "path": "examples/toggle-group-demo.tsx",
      "content": "import { AlignCenter, AlignLeft, AlignRight } from \"lucide-react\";\n\nimport {\n  ToggleGroup,\n  ToggleGroupItem,\n} from \"@/registry/default/ui/toggle-group\";\n\nexport default function ToggleGroupDemo() {\n  return (\n    <ToggleGroup className=\"gap-0.75 rounded-lg border p-0.75\">\n      <ToggleGroupItem value=\"left\" aria-label=\"Toggle left\">\n        <AlignLeft />\n      </ToggleGroupItem>\n      <ToggleGroupItem value=\"center\" aria-label=\"Toggle center\">\n        <AlignCenter />\n      </ToggleGroupItem>\n      <ToggleGroupItem value=\"right\" aria-label=\"Toggle right\">\n        <AlignRight />\n      </ToggleGroupItem>\n    </ToggleGroup>\n  );\n}\n",
      "type": "registry:example",
      "target": ""
    }
  ]
}